pyTRM/__init__.py
pyTRM/pyTRM.py
pyTRM_LuisMunoz-0.1.1.dist-info/LICENSE
pyTRM_LuisMunoz-0.1.1.dist-info/METADATA
pyTRM_LuisMunoz-0.1.1.dist-info/WHEEL
pyTRM_LuisMunoz-0.1.1.dist-info/top_level.txt
pyTRM_LuisMunoz-0.1.1.dist-info/RECORD
