Metadata-Version: 2.1
Name: pyTRM-LuisMunoz
Version: 0.1.1
Summary: Modulo para obtener la TRM - Colombia
Home-page: UNKNOWN
Author: Luis Munoz
Author-email: 
License: UNKNOWN
Platform: UNKNOWN
Classifier: Programming Language :: Python :: 3
Classifier: License :: OSI Approved :: MIT License
License-File: LICENSE
Requires-Dist: requests
